agreementr/__init__.py
agreementr/agreementr.py
agreementr/convert_examples_to_features.py
agreementr/download_features.py
agreementr/old_agreementr.py
agreementr/predict.py
agreementr/preprocess_data.py
agreementr/regression_processor.py
agreementr-1.5.dist-info/METADATA
agreementr-1.5.dist-info/WHEEL
agreementr-1.5.dist-info/top_level.txt
agreementr-1.5.dist-info/RECORD
