Metadata-Version: 2.1
Name: agreementr
Version: 1.5
Summary: agreementr
Home-page: UNKNOWN
Author: Junjie Wu
Author-email: wujj38@mail2.sysu.edu.cn
License: UNKNOWN
Platform: UNKNOWN
Requires-Python: >=3.6
